signapp/__init__.py
signapp/download_tools.py
signapp/signapp.py
signapp-1.0.1.dist-info/METADATA
signapp-1.0.1.dist-info/WHEEL
signapp-1.0.1.dist-info/entry_points.txt
signapp-1.0.1.dist-info/top_level.txt
signapp-1.0.1.dist-info/RECORD
