Metadata-Version: 2.1
Name: signapp
Version: 1.0.1
Summary: Apk signer script
Home-page: https://github.com/mon231/signapp/
Author: Ariel Tubul
Requires-Dist: requests
